spgrep/__init__.py
spgrep/_constants.py
spgrep/core.py
spgrep/corep.py
spgrep/group.py
spgrep/irreps.py
spgrep/pointgroup.py
spgrep/representation.py
spgrep/spinor.py
spgrep/tensor.py
spgrep/transform.py
spgrep/utils.py
spgrep/rep/__init__.py
spgrep/rep/enumerate.py
spgrep/rep/group.py
spgrep/rep/irreps.py
spgrep/rep/pir.py
spgrep/rep/representation.py
spgrep/symmetry/__init__.py
spgrep/symmetry/enumerate.py
spgrep/symmetry/group.py
spgrep/symmetry/pointgroup.py
spgrep/symmetry/representation.py
spgrep/symmetry/subgroup.py
spgrep/symmetry/tensor.py
spgrep/symmetry/transform.py
spgrep-0.5.0.dist-info/licenses/LICENSE
spgrep-0.5.0.dist-info/METADATA
spgrep-0.5.0.dist-info/WHEEL
spgrep-0.5.0.dist-info/top_level.txt
spgrep-0.5.0.dist-info/RECORD
