Metadata-Version: 2.4
Name: spgrep
Version: 0.5.0
Summary: On-the-fly generator of space-group irreducible representations
Author-email: Kohei Shinohara <kshinohara0508@gmail.com>
License: BSD
Project-URL: homepage, https://github.com/spglib/spgrep
Classifier: Development Status :: 3 - Alpha
Classifier: Intended Audience :: Science/Research
Classifier: License :: OSI Approved :: BSD License
Classifier: Operating System :: OS Independent
Classifier: Programming Language :: Python
Classifier: Programming Language :: Python :: 3 :: Only
Classifier: Programming Language :: Python :: 3.10
Classifier: Programming Language :: Python :: 3.11
Classifier: Programming Language :: Python :: 3.12
Classifier: Programming Language :: Python :: 3.13
Classifier: Programming Language :: Python :: 3.14
Classifier: Topic :: Scientific/Engineering :: Mathematics
Classifier: Topic :: Scientific/Engineering :: Physics
Requires-Python: >=3.10.0
License-File: LICENSE
Requires-Dist: hsnf>=0.3.16
Requires-Dist: numpy>=1.20.1
Requires-Dist: spglib>=2.7
Requires-Dist: typing-extensions
Provides-Extra: dev
Requires-Dist: ipykernel; extra == "dev"
Requires-Dist: ipython; extra == "dev"
Requires-Dist: matplotlib; extra == "dev"
Requires-Dist: nbqa; extra == "dev"
Requires-Dist: notebook; extra == "dev"
Requires-Dist: phonopy; extra == "dev"
Requires-Dist: prek; extra == "dev"
Requires-Dist: seaborn; extra == "dev"
Requires-Dist: snakeviz; extra == "dev"
Provides-Extra: docs
Requires-Dist: docutils; extra == "docs"
Requires-Dist: linkify-it-py; extra == "docs"
Requires-Dist: myst-parser; extra == "docs"
Requires-Dist: nbsphinx; extra == "docs"
Requires-Dist: spgrep[dev]; extra == "docs"
Requires-Dist: sphinx; extra == "docs"
Requires-Dist: sphinx-autobuild; extra == "docs"
Requires-Dist: sphinx-book-theme>=0.8; extra == "docs"
Requires-Dist: sphinxcontrib-bibtex>=2.6.2; extra == "docs"
Provides-Extra: testing
Requires-Dist: pytest; extra == "testing"
Requires-Dist: pytest-cov; extra == "testing"
Dynamic: license-file
